[{"Year":2019,"Value":48.4},{"Year":2018,"Value":47.3},{"Year":2017,"Value":49.0},{"Year":2016,"Value":48.4},{"Year":2015,"Value":47.8},{"Year":2014,"Value":46.4},{"Year":2013,"Value":44.1},{"Year":2012,"Value":42.6},{"Year":2011,"Value":43.5},{"Year":2010,"Value":43.2},{"Year":2009,"Value":41.2},{"Year":2008,"Value":42.0},{"Year":2007,"Value":39.7},{"Year":2006,"Value":35.7},{"Year":2005,"Value":34.5},{"Year":2004,"Value":24.7},{"Year":2003,"Value":16.7},{"Year":2002,"Value":8.1},{"Year":2001,"Value":4.6},{"Year":2000,"Value":1.4}]